brc_pytorch/__init__.py
brc_pytorch/datasets/__init__.py
brc_pytorch/datasets/binary_addition.py
brc_pytorch/datasets/brc_dataset.py
brc_pytorch/layers/__init__.py
brc_pytorch/layers/brc_layer.py
brc_pytorch/layers/multilayer_rnnbase.py
brc_pytorch/layers/neuromodulated_brc_layer.py
brc_pytorch/layers/peephole_lstm.py
brc_pytorch/layers/select_item.py
brc_pytorch-0.1.3.dist-info/LICENSE
brc_pytorch-0.1.3.dist-info/METADATA
brc_pytorch-0.1.3.dist-info/WHEEL
brc_pytorch-0.1.3.dist-info/top_level.txt
brc_pytorch-0.1.3.dist-info/RECORD
