Metadata-Version: 2.1
Name: brc-pytorch
Version: 0.1.3
Summary: Pytorch Implementation of BRC.
Home-page: https://github.com/niklexical/brc_pytorch
Author: Nikita Janakarajan, Jannis Born
Author-email: nikita.janakarajan907@gmail.com, jannis.born@gmx.de
License: MIT
Keywords: PyTorch,Deep Learning,RNN,BRC
Platform: UNKNOWN
Classifier: Development Status :: 3 - Alpha
Classifier: Intended Audience :: Developers
Classifier: Topic :: Software Development :: Libraries :: Python Modules
Classifier: License :: OSI Approved :: MIT License
Classifier: Programming Language :: Python :: 3.6
Classifier: Programming Language :: Python :: 3.7
Classifier: Programming Language :: Python :: 3.8
Requires-Dist: numpy
Requires-Dist: torch
